anscom.cp313-win_amd64.pyd
anscom-0.6.0.dist-info/METADATA
anscom-0.6.0.dist-info/WHEEL
anscom-0.6.0.dist-info/top_level.txt
anscom-0.6.0.dist-info/RECORD
