Metadata-Version: 2.4
Name: anscom
Version: 0.6.0
Summary: A fast native C recursive file scanner and analyzer
Home-page: https://github.com/PC5518
Author: Aditya Narayan Singh
Author-email: adityansdsdc@outlook.com
Classifier: Programming Language :: Python :: 3
Classifier: Programming Language :: C
Classifier: License :: OSI Approved :: MIT License
Classifier: Operating System :: OS Independent
Requires-Python: >=3.6
Dynamic: author
Dynamic: author-email
Dynamic: classifier
Dynamic: description
Dynamic: description-content-type
Dynamic: home-page
Dynamic: requires-python
Dynamic: summary
